setup.cfg
setup.py
deepviz/__init__.py
deepviz/intel.py
deepviz/result.py
deepviz/sandbox.py
python_deepviz.egg-info/PKG-INFO
python_deepviz.egg-info/SOURCES.txt
python_deepviz.egg-info/dependency_links.txt
python_deepviz.egg-info/requires.txt
python_deepviz.egg-info/top_level.txt