Metadata-Version: 1.0
Name: python-deepviz
Version: 1.0.3
Summary: Deepviz Threat Intelligence API Client Library for python
Home-page: https://github.com/saferbytes/python-deepviz
Author: Saferbytes
Author-email: info@saferbytes.it
License: MIT
Keywords: deepviz API SDK
Platform: UNKNOWN
